luma.emulator-1.4.0-py3.8-nspkg.pth
luma/emulator/__init__.py
luma/emulator/clut.py
luma/emulator/device.py
luma/emulator/render.py
luma/emulator/segment_mapper.py
luma/emulator/images/7-segment.png
luma/emulator/images/led_off.png
luma/emulator/images/led_on.png
luma.emulator-1.4.0.dist-info/LICENSE.rst
luma.emulator-1.4.0.dist-info/METADATA
luma.emulator-1.4.0.dist-info/WHEEL
luma.emulator-1.4.0.dist-info/namespace_packages.txt
luma.emulator-1.4.0.dist-info/top_level.txt
luma.emulator-1.4.0.dist-info/RECORD
