Metadata-Version: 2.1
Name: luma.emulator
Version: 1.4.0
Summary: A suite of pseudo-devices for luma.core components
Home-page: https://github.com/rm-hull/luma.emulator
Author: Richard Hull
Author-email: richard.hull@destructuring-bind.org
License: MIT
Download-URL: https://github.com/rm-hull/luma.emulator/tarball/1.4.0
Keywords: raspberry orange banana pi rpi opi sbc oled lcd led display screen spi i2c emulator
Platform: UNKNOWN
Classifier: License :: OSI Approved :: MIT License
Classifier: Development Status :: 5 - Production/Stable
Classifier: Intended Audience :: Education
Classifier: Intended Audience :: Developers
Classifier: Topic :: Education
Classifier: Topic :: System :: Hardware
Classifier: Topic :: System :: Hardware :: Hardware Drivers
Classifier: Topic :: Software Development :: Libraries :: pygame
Classifier: Programming Language :: Python :: 3
Classifier: Programming Language :: Python :: 3.6
Classifier: Programming Language :: Python :: 3.7
Classifier: Programming Language :: Python :: 3.8
Classifier: Programming Language :: Python :: 3.9
Requires-Python: >=3.6, <4
Provides-Extra: test
Provides-Extra: qa
Provides-Extra: docs
